unhacs/__init__.py
unhacs/__main__.py
unhacs/git.py
unhacs/main.py
unhacs/packages/__init__.py
unhacs/packages/common.py
unhacs/packages/fork.py
unhacs/packages/integration.py
unhacs/packages/plugin.py
unhacs/packages/theme.py
unhacs/utils.py
unhacs-0.7.2.dist-info/LICENSE
unhacs-0.7.2.dist-info/METADATA
unhacs-0.7.2.dist-info/WHEEL
unhacs-0.7.2.dist-info/entry_points.txt
unhacs-0.7.2.dist-info/RECORD
