Metadata-Version: 2.3
Name: unhacs
Version: 0.7.2
Summary: Command line interface to install Home Assistant Community Store packages
License: MIT
Author: Ian Fijolek
Author-email: ian@iamthefij.com
Requires-Python: >=3.11,<4.0
Classifier: License :: OSI Approved :: MIT License
Classifier: Programming Language :: Python :: 3
Classifier: Programming Language :: Python :: 3.11
Classifier: Programming Language :: Python :: 3.12
Classifier: Programming Language :: Python :: 3.13
Requires-Dist: pyyaml (>=6.0.0,<7.0.0)
Requires-Dist: requests (>=2.32.0,<3.0.0)
